crypto_backtest/__init__.py
crypto_backtest-0.1.0.dist-info/WHEEL
crypto_backtest-0.1.0.dist-info/METADATA
crypto_backtest-0.1.0.dist-info/RECORD
