Metadata-Version: 2.1
Name: crypto-backtest
Version: 0.1.0
Summary: 
Author: Meng Xiangzhuo
Author-email: aumo@foxmail.com
Requires-Python: >=3.11,<4.0
Classifier: Programming Language :: Python :: 3
Classifier: Programming Language :: Python :: 3.11
Requires-Dist: binance-history (>=0.1.5,<0.2.0)
